highcharts_core/__init__.py
highcharts_core/__version__.py
highcharts_core/ai.py
highcharts_core/chart.py
highcharts_core/constants.py
highcharts_core/decorators.py
highcharts_core/errors.py
highcharts_core/headless_export.py
highcharts_core/highcharts.py
highcharts_core/js_literal_functions.py
highcharts_core/metaclasses.py
highcharts_core/module_requirements.json
highcharts_core/utility_functions.py
highcharts_core/global_options/__init__.py
highcharts_core/global_options/shared_options.py
highcharts_core/global_options/language/__init__.py
highcharts_core/global_options/language/export_data.py
highcharts_core/global_options/language/navigation.py
highcharts_core/global_options/language/accessibility/__init__.py
highcharts_core/global_options/language/accessibility/announce_new_data.py
highcharts_core/global_options/language/accessibility/axis.py
highcharts_core/global_options/language/accessibility/chart_types.py
highcharts_core/global_options/language/accessibility/exporting.py
highcharts_core/global_options/language/accessibility/legend.py
highcharts_core/global_options/language/accessibility/navigator.py
highcharts_core/global_options/language/accessibility/range_selector.py
highcharts_core/global_options/language/accessibility/screen_reader_section.py
highcharts_core/global_options/language/accessibility/series.py
highcharts_core/global_options/language/accessibility/sonification.py
highcharts_core/global_options/language/accessibility/table.py
highcharts_core/global_options/language/accessibility/zoom.py
highcharts_core/options/__init__.py
highcharts_core/options/boost.py
highcharts_core/options/caption.py
highcharts_core/options/credits.py
highcharts_core/options/data.py
highcharts_core/options/defs.py
highcharts_core/options/drilldown.py
highcharts_core/options/loading.py
highcharts_core/options/no_data.py
highcharts_core/options/pane.py
highcharts_core/options/responsive.py
highcharts_core/options/subtitle.py
highcharts_core/options/time.py
highcharts_core-1.10.2.dist-info/METADATA
highcharts_core-1.10.2.dist-info/WHEEL
highcharts_core-1.10.2.dist-info/licenses/LICENSE
highcharts_core-1.10.2.dist-info/RECORD
