Metadata-Version: 2.3
Name: highcharts-core
Version: 1.10.2
Summary: High-end Data Visualization for the Python Ecosystem. Official wrapper for Highcharts Core (JS).
Project-URL: Homepage, https://highchartspython.com
Project-URL: Documentation, https://core-docs.highchartspython.com/en/latest/
Project-URL: Support, https://www.highchartspython.com/get-help
Project-URL: Source Code, https://github.com/highcharts-for-python/highcharts-core
Project-URL: History, https://github.com/highcharts-for-python/highcharts-core/blob/master/CHANGES.rst
Project-URL: Bug Tracker, https://github.com/highcharts-for-python/highcharts-core/issues
Project-URL: Demo, https://github.com/highcharts-for-python/highcharts-for-python-demos
Project-URL: Sponsor, https://github.com/sponsors/highcharts-for-python
Author-email: HCP LLC <support@highchartspython.com>
Keywords: charts,data visualization,data viz,graphing,highcharts,highcharts JS,plotting
Classifier: Development Status :: 5 - Production/Stable
Classifier: Environment :: Web Environment
Classifier: Framework :: Jupyter
Classifier: Intended Audience :: Developers
Classifier: Intended Audience :: Education
Classifier: Intended Audience :: Financial and Insurance Industry
Classifier: Intended Audience :: Healthcare Industry
Classifier: Intended Audience :: Manufacturing
Classifier: Intended Audience :: Science/Research
Classifier: License :: Other/Proprietary License
Classifier: Operating System :: OS Independent
Classifier: Topic :: Internet :: WWW/HTTP :: Dynamic Content
Classifier: Topic :: Office/Business
Classifier: Topic :: Scientific/Engineering :: Information Analysis
Classifier: Topic :: Scientific/Engineering :: Visualization
Classifier: Topic :: Software Development :: Code Generators
Classifier: Topic :: Software Development :: Libraries
Classifier: Topic :: Utilities
Requires-Python: >=3.10
Requires-Dist: esprima>=4.0.1
Requires-Dist: requests>=2.32.0
Requires-Dist: validator-collection>=1.5.0
Provides-Extra: ai
Requires-Dist: anthropic>=0.3.11; extra == 'ai'
Requires-Dist: dill>=0.3.7; extra == 'ai'
Requires-Dist: openai>=0.28.0; extra == 'ai'
Provides-Extra: dev
Requires-Dist: anthropic>=0.3.11; extra == 'dev'
Requires-Dist: dill>=0.3.7; extra == 'dev'
Requires-Dist: ipython>=8.10.0; extra == 'dev'
Requires-Dist: openai>=0.28.0; extra == 'dev'
Requires-Dist: orjson>=3.7.7; extra == 'dev'
Requires-Dist: pandas>=1.3.3; extra == 'dev'
Requires-Dist: pyspark>=3.3.0; extra == 'dev'
Requires-Dist: pytest-cov>=3.0.0; extra == 'dev'
Requires-Dist: pytest-xdist>=2.5.0; extra == 'dev'
Requires-Dist: pytest>=7.0.2; extra == 'dev'
Requires-Dist: python-dotenv>=1.0.0; extra == 'dev'
Requires-Dist: pytz>=2022.1; extra == 'dev'
Requires-Dist: sphinx-rtd-theme==1.2.0; extra == 'dev'
Requires-Dist: sphinx-tabs==3.4.1; extra == 'dev'
Requires-Dist: sphinx-toolbox==3.4.0; extra == 'dev'
Requires-Dist: sphinx==6.1.3; extra == 'dev'
Requires-Dist: tox>=4.0.0; extra == 'dev'
Provides-Extra: docs
Requires-Dist: sphinx-rtd-theme==1.2.0; extra == 'docs'
Requires-Dist: sphinx-tabs==3.4.1; extra == 'docs'
Requires-Dist: sphinx-toolbox==3.4.0; extra == 'docs'
Requires-Dist: sphinx==6.1.3; extra == 'docs'
Provides-Extra: soft
Requires-Dist: anthropic>=0.3.11; extra == 'soft'
Requires-Dist: dill>=0.3.7; extra == 'soft'
Requires-Dist: ipython>=8.10.0; extra == 'soft'
Requires-Dist: openai>=0.28.0; extra == 'soft'
Requires-Dist: orjson>=3.7.7; extra == 'soft'
Requires-Dist: pandas>=1.3.3; extra == 'soft'
Requires-Dist: pyspark>=3.3.0; extra == 'soft'
